{"cameraMode":{"drawMode":0,"name":"Shaded","section":"Shading Mode"},"sceneLighting":false,"audioPlay":false,"sceneViewState":{"m_AlwaysRefresh":false,"showFog":true,"showSkybox":false,"showFlares":true,"showImageEffects":true,"showParticleSystems":true,"showVisualEffectGraphs":true,"m_FxEnabled":true},"in2DMode":false,"pivot":{"x":1.865714192390442,"y":-0.8971269726753235,"z":-1.9500672817230225},"rotation":{"x":-0.07476375252008438,"y":-0.9028874039649963,"z":0.1696213185787201,"w":-0.38970839977264407},"size":3.3073947429656984,"orthographic":false}